django_simple_plausible/__init__.py
django_simple_plausible/templatetags/__init__.py
django_simple_plausible/templatetags/plausible.py
django_simple_plausible-0.0.5.dist-info/METADATA
django_simple_plausible-0.0.5.dist-info/WHEEL
django_simple_plausible-0.0.5.dist-info/top_level.txt
django_simple_plausible-0.0.5.dist-info/RECORD
