Metadata-Version: 2.1
Name: django-simple-plausible
Version: 0.0.5
Summary: A simple Django package to render Plausible Analytics html tag
Home-page: https://github.com/T-101/django-simple-plausible
Author: T-101
License: UNKNOWN
Platform: UNKNOWN
Classifier: Programming Language :: Python :: 2
Classifier: Programming Language :: Python :: 3
Classifier: License :: OSI Approved :: MIT License
Classifier: Operating System :: OS Independent
Classifier: Framework :: Django
Classifier: Environment :: Web Environment
Requires-Python: >=2.7
